[{"id":"e1fe5be1.57e508","type":"tab","label":"自動植栽Demo","disabled":false,"info":""},{"id":"181c639c.995cfc","type":"mqtt in","z":"e1fe5be1.57e508","name":"目前氣溫","topic":"hhvs/library/plant/temp","qos":"2","datatype":"auto","broker":"d879983d.6d20b8","nl":false,"rap":true,"rh":0,"x":380,"y":180,"wires":[["d8627fa7.c4b76"]]},{"id":"d8627fa7.c4b76","type":"ui_gauge","z":"e1fe5be1.57e508","name":"","group":"d9a48187.87b37","order":2,"width":5,"height":3,"gtype":"gage","title":"目前空氣溫度","label":"攝氏","format":"{{value}}","min":0,"max":"50","colors":["#7af57a","#f3da58","#ca3838"],"seg1":"","seg2":"","className":"","x":580,"y":180,"wires":[]},{"id":"457e950.5ee006c","type":"mqtt in","z":"e1fe5be1.57e508","name":"目前濕度","topic":"hhvs/library/plant/humi","qos":"2","datatype":"auto","broker":"d879983d.6d20b8","nl":false,"rap":true,"rh":0,"x":380,"y":240,"wires":[["faad5762.d85498","ffdd5bb5.d0b728"]]},{"id":"faad5762.d85498","type":"ui_gauge","z":"e1fe5be1.57e508","name":"","group":"d9a48187.87b37","order":3,"width":5,"height":3,"gtype":"gage","title":"目前空氣濕度","label":"%","format":"{{value}}","min":0,"max":"100","colors":["#a5eaf3","#05bac7","#005064"],"seg1":"","seg2":"","className":"","x":590,"y":240,"wires":[]},{"id":"f8dd4291.bb02c","type":"mqtt in","z":"e1fe5be1.57e508","name":"土壤濕度","topic":"hhvs/library/plant/moisture","qos":"2","datatype":"auto","broker":"d879983d.6d20b8","nl":false,"rap":true,"rh":0,"x":380,"y":320,"wires":[["d451d007.9b9e5"]]},{"id":"d451d007.9b9e5","type":"ui_gauge","z":"e1fe5be1.57e508","name":"","group":"49e1101a.47966","order":4,"width":5,"height":3,"gtype":"gage","title":"土壤濕度","label":"units","format":"{{value}}","min":0,"max":"4096","colors":["#f7bd88","#f9861a","#803e00"],"seg1":"","seg2":"","className":"","x":570,"y":340,"wires":[]},{"id":"a45c8070.13bc1","type":"ui_switch","z":"e1fe5be1.57e508","name":"","label":"水泵開關","tooltip":"","group":"49e1101a.47966","order":2,"width":3,"height":1,"passthru":true,"decouple":"false","topic":"topic","topicType":"msg","style":"","onvalue":"true","onvalueType":"bool","onicon":"","oncolor":"","offvalue":"false","offvalueType":"bool","officon":"","offcolor":"","animate":false,"className":"","x":350,"y":460,"wires":[["bfc9d85b.d72ce8","627d0fa3.9ae2d"]]},{"id":"97c3050e.ffff98","type":"mqtt out","z":"e1fe5be1.57e508","name":"","topic":"hhvs/library/plant/pump","qos":"","retain":"","respTopic":"","contentType":"","userProps":"","correl":"","expiry":"","broker":"d879983d.6d20b8","x":770,"y":460,"wires":[]},{"id":"bfc9d85b.d72ce8","type":"function","z":"e1fe5be1.57e508","name":"","func":"if(msg.payload == true )\n  msg.payload = \"ON\";\nelse\n  msg.payload = \"OFF\";\nreturn msg;","outputs":1,"noerr":0,"initialize":"","finalize":"","libs":[],"x":550,"y":460,"wires":[["97c3050e.ffff98"]]},{"id":"627d0fa3.9ae2d","type":"ui_led","z":"e1fe5be1.57e508","order":1,"group":"49e1101a.47966","width":1,"height":1,"label":"","labelPlacement":"left","labelAlignment":"left","colorForValue":[{"color":"#08685d","value":"false","valueType":"bool"},{"color":"#08fdb3","value":"true","valueType":"bool"}],"allowColorForValueInMessage":false,"shape":"circle","showGlow":true,"name":"","x":480,"y":540,"wires":[]},{"id":"b5884cf4.776e8","type":"inject","z":"e1fe5be1.57e508","name":"","props":[{"p":"payload"}],"repeat":"1","crontab":"","once":true,"onceDelay":0.1,"topic":"","payload":"","payloadType":"date","x":300,"y":100,"wires":[["db3cb483.88c328"]]},{"id":"db3cb483.88c328","type":"ui_clock","z":"e1fe5be1.57e508","name":"","group":"d9a48187.87b37","order":1,"width":4,"height":3,"x":650,"y":100,"wires":[],"inputLabels":["a"]},{"id":"b124ab71.1b8c68","type":"ui_template","z":"e1fe5be1.57e508","group":"49e1101a.47966","name":"","order":5,"width":2,"height":1,"format":"<style>\n:root {\n  --color-green-primary: rgb(51, 204, 51);\n  --color-green-secondary: rgb(26, 101, 26);\n  --color-red-primary: rgb(255, 0, 0);\n  --color-red-secondary: rgba(153,0,0,1);\n  --color-gray-primary:rgba(40,40,40,1);\n  --color-gray-secondary:rgba(65,65,65,1);\n  --color-text-primary: rgb(0, 0, 0);\n  --color-widget-border: rgb(84, 78, 78);\n}\n\nbody {\n  background-image: url('/plant.jpg');\n  background-repeat: no-repeat;\n  background-size: cover;\n}\n\n</style>","storeOutMessages":true,"fwdInMessages":true,"resendOnRefresh":true,"templateScope":"local","className":"","x":270,"y":580,"wires":[[]]},{"id":"ffdd5bb5.d0b728","type":"ui_level","z":"e1fe5be1.57e508","group":"d9a48187.87b37","order":4,"width":2,"height":3,"name":"","label":"","colorHi":"#e60000","colorWarn":"#ff9900","colorNormal":"#00b33c","colorOff":"#595959","min":0,"max":100,"segWarn":"","segHigh":"","unit":"","layout":"sv","channelA":"","channelB":"","decimals":0,"animations":"soft","shape":2,"colorschema":"fixed","textoptions":"default","colorText":"#eeeeee","fontLabel":"","fontValue":"","fontSmall":"","colorFromTheme":true,"textAnimations":true,"hideValue":false,"tickmode":"auto","peakmode":false,"property":"payload","peaktime":3000,"x":750,"y":300,"wires":[]},{"id":"46916ffa.2c91","type":"mqtt in","z":"e1fe5be1.57e508","name":"空氣灰塵值","topic":"hhvs/library/plant/sharpSensor","qos":"2","datatype":"auto","broker":"d879983d.6d20b8","nl":false,"rap":true,"rh":0,"x":380,"y":380,"wires":[["e61fc27d.8c1"]]},{"id":"e61fc27d.8c1","type":"ui_gauge","z":"e1fe5be1.57e508","name":"","group":"626a7629.447aa8","order":1,"width":5,"height":4,"gtype":"gage","title":"灰塵值","label":"units","format":"{{value}}","min":0,"max":"5000","colors":["#00b500","#f5f500","#ca3838"],"seg1":"300","seg2":"1050","className":"","x":560,"y":400,"wires":[]},{"id":"d879983d.6d20b8","type":"mqtt-broker","name":"EMQX","broker":"broker.emqx.io","port":"1883","clientid":"","usetls":false,"compatmode":false,"protocolVersion":4,"keepalive":"60","cleansession":true,"birthTopic":"","birthQos":"0","birthPayload":"","closeTopic":"","closeQos":"0","closePayload":"","willTopic":"","willQos":"0","willPayload":""},{"id":"d9a48187.87b37","type":"ui_group","name":"時間","tab":"430b6af1.132aa4","order":1,"disp":false,"width":16,"collapse":false,"className":""},{"id":"49e1101a.47966","type":"ui_group","name":"土壤狀態","tab":"430b6af1.132aa4","order":2,"disp":false,"width":"5","collapse":false,"className":""},{"id":"626a7629.447aa8","type":"ui_group","name":"空氣品質","tab":"430b6af1.132aa4","order":3,"disp":true,"width":"5","collapse":false,"className":""},{"id":"430b6af1.132aa4","type":"ui_tab","name":"自動化植栽Demo","icon":"dashboard","order":10,"disabled":false,"hidden":false}]